apiTestHttp/__init__.py
apiTestHttp/apitest.py
apiTestHttp/uitest.py
apitestbasiclib/__init__.py
apitestbasiclib/apibasic.py
apitestbasiclib/apirequest.py
apitestbasiclib/apitestlogic.py
apitestbasiclib/dbutils.py
apitestbasiclib/filetools.py
apitestbasiclib/jsoncompare.py
apitestbasiclib/log.py
apiTestBasicLib-0.0.1.dist-info/METADATA
apiTestBasicLib-0.0.1.dist-info/WHEEL
apiTestBasicLib-0.0.1.dist-info/top_level.txt
apiTestBasicLib-0.0.1.dist-info/RECORD
