Metadata-Version: 2.1
Name: apiTestBasicLib
Version: 0.0.1
Summary: HTTP接口测试脚本工具库
Home-page: UNKNOWN
Author: wuweiping
Author-email: wuweiping@xforceplus.com
Maintainer: wuweiping
Maintainer-email: wuweiping@xforceplus.com
License: UNKNOWN
Platform: UNKNOWN
Requires-Python: >=3.6
Requires-Dist: xfctRftHttpStep (>=0.1.1)
Requires-Dist: xfctRftBasic (>=0.1.3)
